CHANGES.txt
README.txt
bootstrap.py
buildout.cfg
setup.py
versions.cfg
src/megrok/__init__.py
src/megrok.pagelet.egg-info/PKG-INFO
src/megrok.pagelet.egg-info/SOURCES.txt
src/megrok.pagelet.egg-info/dependency_links.txt
src/megrok.pagelet.egg-info/entry_points.txt
src/megrok.pagelet.egg-info/namespace_packages.txt
src/megrok.pagelet.egg-info/not-zip-safe
src/megrok.pagelet.egg-info/requires.txt
src/megrok.pagelet.egg-info/top_level.txt
src/megrok/pagelet/README.txt
src/megrok/pagelet/__init__.py
src/megrok/pagelet/component.py
src/megrok/pagelet/directive.py
src/megrok/pagelet/ftesting.zcml
src/megrok/pagelet/meta.py
src/megrok/pagelet/meta.zcml
src/megrok/pagelet/tests/__init__.py
src/megrok/pagelet/tests/test_layout.py
src/megrok/pagelet/tests/test_pagelet.py
src/megrok/pagelet/tests/test_pagelet_layers.py
src/megrok/pagelet/tests/templates/context_layout.pt
src/megrok/pagelet/tests/templates/house.pt
src/megrok/pagelet/tests/templates/layer_layout.pt
src/megrok/pagelet/tests/templates/layout.pt
src/megrok/pagelet/tests/templates/playout.pt
src/megrok/pagelet/tests/test_pagelet_templates/pageletwithtemplate.pt