Metadata-Version: 1.0
Name: megrok.pagelet
Version: 0.1
Summary: z3c.template / z3c.layout support for Grok
Home-page: http://pypi.python.org/pypi/megrok.pagelet
Author: UNKNOWN
Author-email: UNKNOWN
License: ZPL
Platform: UNKNOWN
Classifier: Programming Language :: Python
Classifier: Environment :: Web Environment
Classifier: Framework :: Zope3
Classifier: License :: OSI Approved :: Zope Public License
